wannier90_input/patches.py
wannier90_input/__init__.py
wannier90_input/version.py
wannier90_input/fetch.py
wannier90_input/convert.py
wannier90_input/__main__.py
wannier90_input/cli.py
wannier90_input/xml_files/__init__.py
wannier90_input/xml_files/latest/parameters.xml
wannier90_input/xml_files/0a0a3e5/parameters.xml
wannier90_input/models/__init__.py
wannier90_input/models/template.py
wannier90_input/models/latest.py
wannier90_input/models/sha_0a0a3e5.py
wannier90_input/models/keywords.txt
wannier90_input/models/parameters.py
wannier90_input/py.typed
wannier90_input/generate.py
wannier90_input-0.0.1.dist-info/licenses/LICENSE
wannier90_input-0.0.1.dist-info/WHEEL
wannier90_input-0.0.1.dist-info/entry_points.txt
wannier90_input-0.0.1.dist-info/METADATA
wannier90_input-0.0.1.dist-info/RECORD
