Metadata-Version: 2.4
Name: wannier90-input
Version: 0.0.1
Summary: Pydantic models for the input of Wannier90
Keywords: snekpack,cookiecutter
Author: Edward Linscott
Author-email: Edward Linscott <edwardlinscott@gmail.com>
License-File: LICENSE
Classifier: Development Status :: 1 - Planning
Classifier: Environment :: Console
Classifier: Intended Audience :: Developers
Classifier: License :: OSI Approved :: MIT License
Classifier: Operating System :: OS Independent
Classifier: Framework :: Pytest
Classifier: Framework :: tox
Classifier: Framework :: Sphinx
Classifier: Natural Language :: English
Classifier: Programming Language :: Python
Classifier: Programming Language :: Python :: 3.10
Classifier: Programming Language :: Python :: 3.11
Classifier: Programming Language :: Python :: 3.12
Classifier: Programming Language :: Python :: 3.13
Classifier: Programming Language :: Python :: 3 :: Only
Classifier: Typing :: Typed
Requires-Dist: more-itertools
Requires-Dist: tqdm
Requires-Dist: click
Requires-Dist: more-click
Requires-Dist: typing-extensions
Requires-Dist: github3-py
Requires-Dist: pydantic>=2.0
Requires-Dist: numpy>=2.0
Requires-Dist: defusedxml
Maintainer: Edward Linscott
Maintainer-email: Edward Linscott <edwardlinscott@gmail.com>
Requires-Python: >=3.10
Project-URL: Bug Tracker, https://github.com/elinscott/wannier90-input/issues
Project-URL: Documentation, https://wannier90_input.readthedocs.io
Project-URL: Funding, https://github.com/sponsors/elinscott
Project-URL: Homepage, https://github.com/elinscott/wannier90-input
Project-URL: Repository, https://github.com/elinscott/wannier90-input.git
